pyvem/__init__.py
pyvem/cli.py
pyvem/core.py
pyvem/commands/__init__.py
pyvem/commands/activate.py
pyvem/commands/base.py
pyvem/commands/create.py
pyvem/commands/list.py
pyvem/commands/req.py
pyvem-0.0.1.dist-info/METADATA
pyvem-0.0.1.dist-info/WHEEL
pyvem-0.0.1.dist-info/entry_points.txt
pyvem-0.0.1.dist-info/top_level.txt
pyvem-0.0.1.dist-info/RECORD
