Metadata-Version: 2.1
Name: pyvem
Version: 0.0.1
Summary: A command line program for managing Python virutal environments.
Home-page: UNKNOWN
Author: Brian Sacash
Author-email: 
License: UNLICENSE
Keywords: cli
Platform: UNKNOWN
Classifier: Intended Audience :: Developers
Classifier: Topic :: Utilities
Classifier: License :: Public Domain
Classifier: Natural Language :: English
Classifier: Operating System :: POSIX
Classifier: Programming Language :: Python :: 3.6
Classifier: Programming Language :: Python :: 3.7
Requires-Dist: docopt
Requires-Dist: virtualenv
Provides-Extra: test
Requires-Dist: coverage ; extra == 'test'
Requires-Dist: pytest ; extra == 'test'
Requires-Dist: pytest-cov ; extra == 'test'
